athleteprofiler/__init__.py
athleteprofiler/src/__init__.py
athleteprofiler/src/athlete.py
athleteprofiler/src/examples.py
athleteprofiler/src/vo2_max_data.py
athleteprofiler/test/__init__.py
athleteprofiler/test/test_athlete.py
athleteprofiler-0.1.1.dist-info/LICENSE
athleteprofiler-0.1.1.dist-info/METADATA
athleteprofiler-0.1.1.dist-info/WHEEL
athleteprofiler-0.1.1.dist-info/top_level.txt
athleteprofiler-0.1.1.dist-info/RECORD
